sent_pattern/__init__.py
sent_pattern/tags.py
sent_pattern/core/__init__.py
sent_pattern/core/type.py
sent_pattern/core/elements/__init__.py
sent_pattern/core/elements/adjective.py
sent_pattern/core/elements/elements.py
sent_pattern/core/elements/object.py
sent_pattern/core/elements/patterns.py
sent_pattern/core/elements/subject.py
sent_pattern/core/elements/verb.py
sent_pattern/core/elements/sub/__init__.py
sent_pattern/core/elements/sub/phrase.py
sent_pattern/core/elements/sub/relative.py
sent_pattern/core/interface/Ielement.py
sent_pattern/core/interface/Ipattern.py
sent_pattern/core/interface/__init__.py
sent_pattern/pipelines/__init__.py
sent_pattern/pipelines/sent_pattern.py
sent_pattern/pipelines/span_noun.py
sent_pattern/pipelines/sub_texts.py
test/__init__.py
test/test_element.py
test/test_phrase.py
test/test_sentpattern.py
test/test_sents.py
test/test_tag.py
sent_pattern-0.1.2.dist-info/LICENCE
sent_pattern-0.1.2.dist-info/METADATA
sent_pattern-0.1.2.dist-info/WHEEL
sent_pattern-0.1.2.dist-info/entry_points.txt
sent_pattern-0.1.2.dist-info/top_level.txt
sent_pattern-0.1.2.dist-info/RECORD
