Metadata-Version: 2.1
Name: sent-pattern
Version: 0.1.2
Summary: project that interpret English sentences to improve your ability to read English sentences correctly.
Home-page: https://github.com/lll-lll-lll-lll/sent-pattern
Author: Shunpei Nakayama
Author-email: hoku804049@gmail.com
License: MIT
Classifier: Programming Language :: Python :: 3
Classifier: License :: OSI Approved :: MIT License
Requires-Python: >=3.8
License-File: LICENCE
Requires-Dist: spacy (>=3.3.1)
